{
  "admin": [
    {
      "userID": "2501001",
      "password": "Karthik@123",
      "id": "528c"
    }
  ],
  "operator": [
    {
      "userID": "25OP001",
      "password": "Karthik@1806",
      "firstName": "John",
      "lastName": "Smith",
      "email": "john.smith@email.com",
      "phone": "+1-555-0101",
      "status": "active",
      "id": "0a47"
    },
    {
      "userID": "25OP002",
      "password": "Op@456",
      "firstName": "Sarah",
      "lastName": "Johnson",
      "email": "sarah.johnson@email.com",
      "phone": "+1-555-0102",
      "status": "active",
      "id": "a240"
    },
    {
      "userID": "25OP003",
      "password": "Op@789",
      "firstName": "Mike",
      "lastName": "Davis",
      "email": "mike.davis@email.com",
      "phone": "+1-555-0103",
      "status": "active",
      "id": "2ead"
    },
    {
      "userID": "25OP004",
      "password": "Op@321",
      "firstName": "Emily",
      "lastName": "Brown",
      "email": "emily.brown@email.com",
      "phone": "+1-555-0104",
      "status": "active",
      "id": "432b"
    },
    {
      "userID": "25OP005",
      "password": "Op@654",
      "firstName": "David",
      "lastName": "Wilson",
      "email": "david.wilson@email.com",
      "phone": "+1-555-0105",
      "status": "active",
      "id": "1e1d"
    },
    {
      "userID": "25OP006",
      "password": "Op@987",
      "firstName": "Lisa",
      "lastName": "Garcia",
      "email": "lisa.garcia@email.com",
      "phone": "+1-555-0106",
      "status": "active",
      "id": "8d9b"
    },
    {
      "userID": "25OP007",
      "password": "Op@147",
      "firstName": "Robert",
      "lastName": "Martinez",
      "email": "robert.martinez@email.com",
      "phone": "+1-555-0107",
      "status": "active",
      "id": "67d4"
    },
    {
      "userID": "25OP008",
      "password": "Op@258",
      "firstName": "Jennifer",
      "lastName": "Anderson",
      "email": "jennifer.anderson@email.com",
      "phone": "+1-555-0108",
      "status": "active",
      "id": "3234"
    },
    {
      "userID": "25OP009",
      "password": "Op@369",
      "firstName": "Chris",
      "lastName": "Taylor",
      "email": "chris.taylor@email.com",
      "phone": "+1-555-0109",
      "status": "active",
      "id": "ae96"
    },
    {
      "userID": "25OP010",
      "password": "Op@741",
      "firstName": "Amanda",
      "lastName": "Thomas",
      "email": "amanda.thomas@email.com",
      "phone": "+1-555-0110",
      "status": "active",
      "id": "a0b2"
    },
    {
      "id": "fd76",
      "userID": "26OP011",
      "password": "UZvHKZaO",
      "firstName": "Vishnu",
      "lastName": "Reddy",
      "email": "vishnuvardhanreddy1029@gmail.com",
      "phone": "9293218577",
      "status": "active"
    },
    {
      "id": "2042",
      "userID": "26OP012",
      "password": "b70Z2k5h",
      "firstName": "karthik",
      "lastName": "dorashetty",
      "email": "dorashettykarthik92@gmail.com",
      "phone": "9866442051",
      "status": "active"
    }
  ],
  "pendingOperators": []
}